{".class": "MypyFile", "_fullname": "discord.state", "future_import_flags": [], "is_partial_stub_package": false, "is_stub": true, "names": {".class": "SymbolTable", "AutoShardedConnectionState": {".class": "SymbolTableNode", "kind": "Gdef", "node": {".class": "TypeInfo", "_promote": null, "abstract_attributes": [], "bases": ["discord.state.ConnectionState"], "declared_metaclass": null, "defn": {".class": "ClassDef", "fullname": "discord.state.AutoShardedConnectionState", "name": "AutoShardedConnectionState", "type_vars": []}, "flags": [], "fullname": "discord.state.AutoShardedConnectionState", "metaclass_type": null, "metadata": {}, "module_name": "discord.state", "mro": ["discord.state.AutoShardedConnectionState", "discord.state.ConnectionState", "builtins.object"], "names": {".class": "SymbolTable"}, "tuple_type": null, "type_vars": [], "typeddict_type": null}}, "ConnectionState": {".class": "SymbolTableNode", "kind": "Gdef", "node": {".class": "TypeInfo", "_promote": null, "abstract_attributes": [], "bases": ["builtins.object"], "declared_metaclass": null, "defn": {".class": "ClassDef", "fullname": "discord.state.ConnectionState", "name": "ConnectionState", "type_vars": []}, "flags": [], "fullname": "discord.state.ConnectionState", "metaclass_type": null, "metadata": {}, "module_name": "discord.state", "mro": ["discord.state.ConnectionState", "builtins.object"], "names": {".class": "SymbolTable"}, "tuple_type": null, "type_vars": [], "typeddict_type": null}}, "__doc__": {".class": "SymbolTableNode", "kind": "Gdef", "node": {".class": "Var", "flags": ["is_ready"], "fullname": "discord.state.__doc__", "name": "__doc__", "type": "builtins.str"}}, "__file__": {".class": "SymbolTableNode", "kind": "Gdef", "node": {".class": "Var", "flags": ["is_ready"], "fullname": "discord.state.__file__", "name": "__file__", "type": "builtins.str"}}, "__name__": {".class": "SymbolTableNode", "kind": "Gdef", "node": {".class": "Var", "flags": ["is_ready"], "fullname": "discord.state.__name__", "name": "__name__", "type": "builtins.str"}}, "__package__": {".class": "SymbolTableNode", "kind": "Gdef", "node": {".class": "Var", "flags": ["is_ready"], "fullname": "discord.state.__package__", "name": "__package__", "type": "builtins.str"}}}, "path": "/home/ava/.local/lib/python3.8/site-packages/discord-stubs/state.pyi"}